[{"Content": "Very good but crashes everytime my data signal gets low", "Numbers": "1", "Date": "February 1, 2017"}, {"Content": "Doesn't work on Sony z2 or m4 aqua\nWhen I try to open the app it crashes and gives me the unfortunately ljngvist has crashed screen. I'll wait till the next update they have to see if they have fixed the issue. If not I'm uninstalling it. Unfortunate since I enjoy using lingvist on my laptop and my itouch. I hate it when I see an app better designed for the ios than android.", "Numbers": "2", "Date": "November 21, 2015"}, {"Content": "Crashes Seems to be something I would use but it's not working. Doesn't launch and crashes immediately. I hope it will be fixed soon. I don't like giving one stars but I guess that's how they see what's up...", "Numbers": "3", "Date": "April 25, 2016"}, {"Content": "The app does not open. It just crashes if i try to open it.", "Numbers": "4", "Date": "October 5, 2017"}]